[
    {
        "_id": "612793e72867ec64bc614241",
        "owner": "6125a68825da1551301faac1",
        "post": "6125aa1c5f545a4b301788b1",
        "content": "Boring!!!",
        "created_at": 1576506719083
    },
    {
        "_id": "612793e72867ec64bc614242",
        "owner": "6125a68825da1551301faac3",
        "post": "6125aa1c5f545a4b301788b3",
        "content": "Very good. But very bad also",
        "created_at": 1576506719083
    },
    {
        "_id": "612793e72867ec64bc614243",
        "owner": "6125a68825da1551301faac2",
        "post": "6125aa1c5f545a4b301788b2",
        "content": "Delightful unreserved impossible few estimating men favourable see entreaties. She propriety immediate was improving. He or entrance humoured likewise moderate. Much nor game son say feel. Fat make met can must form into gate. Me we offending prevailed discovery. ",
        "created_at": 1576506719083
    }
]